kv/api/__init__.py
kv/api/__init__.pyi
kv/api/conn_strings.py
kv/api/errors.py
kv/api/impl.py
kv/api/kv.py
kv/api/extensions/__init__.py
kv/api/extensions/__init__.pyi
kv/api/extensions/append.py
kv/api/extensions/locate.py
kv_api-0.1.24.dist-info/METADATA
kv_api-0.1.24.dist-info/WHEEL
kv_api-0.1.24.dist-info/top_level.txt
kv_api-0.1.24.dist-info/RECORD
