Metadata-Version: 2.1
Name: kv-api
Version: 0.1.24
Summary: Interface for any Key-Value DB. Completely exception-free, and backed by `haskellian` for powerful composability
Author-email: Marcel Claramunt <marcel@moveread.com>
Project-URL: repo, https://github.com/marciclabas/python-storage
Project-URL: home, https://github.com/marciclabas/python-storage/tree/main/kv/kv-api
Requires-Python: >=3.10
Requires-Dist: haskellian
Requires-Dist: lazy-loader
Requires-Dist: typing-extensions
